simpleynews/__init__.py
simpleynews/simpleynews.py
simpleynews-0.3.1.dist-info/LICENSE
simpleynews-0.3.1.dist-info/METADATA
simpleynews-0.3.1.dist-info/WHEEL
simpleynews-0.3.1.dist-info/top_level.txt
simpleynews-0.3.1.dist-info/RECORD
