Metadata-Version: 2.1
Name: simpleynews
Version: 0.3.1
Summary: A simple Yahoo Finance news scraper
Home-page: https://gitlab.com/CochainComplex/simpleynews
Author: Alexander Warth
Author-email: alexander.warth@mailbox.org
Classifier: Development Status :: 4 - Beta
Classifier: Intended Audience :: Developers
Classifier: License :: OSI Approved :: Apache Software License
Classifier: Operating System :: OS Independent
Classifier: Programming Language :: Python :: 3
Classifier: Programming Language :: Python :: 3.6
Classifier: Programming Language :: Python :: 3.7
Classifier: Programming Language :: Python :: 3.8
Classifier: Programming Language :: Python :: 3.9
Requires-Python: >=3.6
License-File: LICENSE
Requires-Dist: requests
Requires-Dist: beautifulsoup4
Requires-Dist: pytz
